[
	{
		"inputs": [],
		"stateMutability": "nonpayable",
		"type": "constructor"
	},
	{
		"anonymous": false,
		"inputs": [
			{
				"indexed": false,
				"internalType": "bytes32",
				"name": "proofName",
				"type": "bytes32"
			},
			{
				"indexed": false,
				"internalType": "bytes32",
				"name": "proof",
				"type": "bytes32"
			}
		],
		"name": "ProofStored",
		"type": "event"
	},
	{
		"inputs": [
			{
				"internalType": "bytes32",
				"name": "proofName",
				"type": "bytes32"
			}
		],
		"name": "getProof",
		"outputs": [
			{
				"internalType": "bytes32",
				"name": "",
				"type": "bytes32"
			}
		],
		"stateMutability": "view",
		"type": "function"
	},
	{
		"inputs": [],
		"name": "owner",
		"outputs": [
			{
				"internalType": "address",
				"name": "",
				"type": "address"
			}
		],
		"stateMutability": "view",
		"type": "function"
	},
	{
		"inputs": [
			{
				"internalType": "bytes32",
				"name": "",
				"type": "bytes32"
			}
		],
		"name": "proofs",
		"outputs": [
			{
				"internalType": "bytes32",
				"name": "",
				"type": "bytes32"
			}
		],
		"stateMutability": "view",
		"type": "function"
	},
	{
		"inputs": [
			{
				"internalType": "bytes32",
				"name": "proofName",
				"type": "bytes32"
			},
			{
				"internalType": "bytes32",
				"name": "proof",
				"type": "bytes32"
			}
		],
		"name": "storeProof",
		"outputs": [],
		"stateMutability": "nonpayable",
		"type": "function"
	}
]